cosmic_ray_spor_filter/__init__.py
cosmic_ray_spor_filter/cli.py
cosmic_ray_spor_filter/filter.py
cosmic_ray_spor_filter/version.py
cosmic_ray_spor_filter-1.0.0.dist-info/LICENSE
cosmic_ray_spor_filter-1.0.0.dist-info/METADATA
cosmic_ray_spor_filter-1.0.0.dist-info/WHEEL
cosmic_ray_spor_filter-1.0.0.dist-info/entry_points.txt
cosmic_ray_spor_filter-1.0.0.dist-info/top_level.txt
cosmic_ray_spor_filter-1.0.0.dist-info/RECORD
