Metadata-Version: 2.1
Name: cosmic-ray-spor-filter
Version: 1.0.0
Summary: Spor-based filter for Cosmic Ray mutation testing
Home-page: http://github.com/abingham/cosmic-ray-spor-filter
Author: Austin Bingham
Author-email: austin.bingham@gmail.com
License: MIT
Platform: any
Classifier: Development Status :: 3 - Alpha
Classifier: Operating System :: OS Independent
Classifier: Programming Language :: Python
Classifier: Programming Language :: Python :: 3 :: Only
Requires-Dist: cosmic-ray
Requires-Dist: spor-python
Provides-Extra: dev
Requires-Dist: bumpversion ; extra == 'dev'
Provides-Extra: test
Requires-Dist: hypothesis ; extra == 'test'
Requires-Dist: pytest ; extra == 'test'
